certego_saas/__init__.py
certego_saas/apps.py
certego_saas/models.py
certego_saas/settings.py
certego_saas/urls.py
certego_saas/version.py
certego_saas/apps/__init__.py
certego_saas/apps/auth/__init__.py
certego_saas/apps/auth/apps.py
certego_saas/apps/auth/backend.py
certego_saas/apps/auth/urls.py
certego_saas/apps/auth/views.py
certego_saas/apps/feedback/__init__.py
certego_saas/apps/feedback/admin.py
certego_saas/apps/feedback/apps.py
certego_saas/apps/feedback/models.py
certego_saas/apps/feedback/serializers.py
certego_saas/apps/feedback/urls.py
certego_saas/apps/feedback/views.py
certego_saas/apps/feedback/migrations/0001_initial.py
certego_saas/apps/feedback/migrations/__init__.py
certego_saas/apps/notifications/__init__.py
certego_saas/apps/notifications/admin.py
certego_saas/apps/notifications/apps.py
certego_saas/apps/notifications/filters.py
certego_saas/apps/notifications/models.py
certego_saas/apps/notifications/serializers.py
certego_saas/apps/notifications/urls.py
certego_saas/apps/notifications/views.py
certego_saas/apps/notifications/management/__init__.py
certego_saas/apps/notifications/management/commands/__init__.py
certego_saas/apps/notifications/management/commands/changelog_notification.py
certego_saas/apps/notifications/migrations/0001_initial.py
certego_saas/apps/notifications/migrations/0002_alter_notification_appname.py
certego_saas/apps/notifications/migrations/0003_for_user.py
certego_saas/apps/notifications/migrations/0004_for_user_blank.py
certego_saas/apps/notifications/migrations/__init__.py
certego_saas/apps/organization/__init__.py
certego_saas/apps/organization/admin.py
certego_saas/apps/organization/apps.py
certego_saas/apps/organization/invitation.py
certego_saas/apps/organization/membership.py
certego_saas/apps/organization/mixins.py
certego_saas/apps/organization/models.py
certego_saas/apps/organization/organization.py
certego_saas/apps/organization/permissions.py
certego_saas/apps/organization/serializers.py
certego_saas-0.7.11.dist-info/LICENSE
certego_saas-0.7.11.dist-info/METADATA
certego_saas-0.7.11.dist-info/WHEEL
certego_saas-0.7.11.dist-info/top_level.txt
certego_saas-0.7.11.dist-info/RECORD
