Metadata-Version: 2.1
Name: certego_saas
Version: 0.7.11
Summary: Certego SaaS
Home-page: https://github.com/certego/certego-saas
Author: Certego S.R.L
License: MIT
Project-URL: Documentation, https://github.com/certego/certego-saas
Project-URL: Source, https://github.com/certego/certego-saas
Project-URL: Tracker, https://github.com/certego/certego-saas/issues
Keywords: certego django rest framework saas
Classifier: Intended Audience :: Developers
Classifier: License :: OSI Approved :: BSD License
Classifier: Programming Language :: Python :: 3.8
Classifier: Programming Language :: Python :: 3.9
Classifier: Programming Language :: Python :: 3.10
Classifier: Topic :: Software Development :: Libraries :: Python Modules
Requires-Python: >=3.8
License-File: LICENSE
Requires-Dist: Django>=2.2.0
Requires-Dist: django-filter>=21.1
Requires-Dist: django-cache-memoize>=0.1.10
Requires-Dist: django-user-agents>=0.4.0
Requires-Dist: djangorestframework>=3.12.0
Requires-Dist: drf-spectacular>=0.21.1
Requires-Dist: drf-flex-fields>=0.9.6
Requires-Dist: djangorestframework-filters>=1.0.0.dev2
Requires-Dist: django-email-utils<2.0,>=1.0
Requires-Dist: django-rest-durin==1.0.0
Requires-Dist: drf-recaptcha>=2.0.7
Requires-Dist: slack-sdk>=3.11.2
Requires-Dist: stripe>=2.61.0
Requires-Dist: python-twitter~=3.5
Requires-Dist: Markdown~=3.3.6
Requires-Dist: elasticsearch>=6.0.0
Provides-Extra: dev
Requires-Dist: Django>=2.2.0; extra == "dev"
Requires-Dist: django-filter>=21.1; extra == "dev"
Requires-Dist: django-cache-memoize>=0.1.10; extra == "dev"
Requires-Dist: django-user-agents>=0.4.0; extra == "dev"
Requires-Dist: djangorestframework>=3.12.0; extra == "dev"
Requires-Dist: drf-spectacular>=0.21.1; extra == "dev"
Requires-Dist: drf-flex-fields>=0.9.6; extra == "dev"
Requires-Dist: djangorestframework-filters>=1.0.0.dev2; extra == "dev"
Requires-Dist: django-email-utils<2.0,>=1.0; extra == "dev"
Requires-Dist: django-rest-durin==1.0.0; extra == "dev"
Requires-Dist: drf-recaptcha>=2.0.7; extra == "dev"
Requires-Dist: slack-sdk>=3.11.2; extra == "dev"
Requires-Dist: stripe>=2.61.0; extra == "dev"
Requires-Dist: python-twitter~=3.5; extra == "dev"
Requires-Dist: Markdown~=3.3.6; extra == "dev"
Requires-Dist: elasticsearch>=6.0.0; extra == "dev"
Requires-Dist: flake8==4.0.1; extra == "dev"
Requires-Dist: black==22.3.0; extra == "dev"
Requires-Dist: isort==5.10.1; extra == "dev"
Requires-Dist: pylint~=2.12.2; extra == "dev"
Requires-Dist: pylint-django~=2.4.4; extra == "dev"
Requires-Dist: mypy==0.910; extra == "dev"
Requires-Dist: django-stubs==1.9.0; extra == "dev"
Requires-Dist: djangorestframework-stubs==1.4.0; extra == "dev"
Requires-Dist: types-Markdown==3.3.12; extra == "dev"
Requires-Dist: coverage~=6.2; extra == "dev"
Requires-Dist: tox; extra == "dev"
Requires-Dist: tox-gh-actions; extra == "dev"
